sparkx/BaseStorer.py
sparkx/BulkObservables.py
sparkx/CentralityClasses.py
sparkx/EventCharacteristics.py
sparkx/Filter.py
sparkx/Histogram.py
sparkx/Jackknife.py
sparkx/JetAnalysis.py
sparkx/Jetscape.py
sparkx/Lattice3D.py
sparkx/MultiParticlePtCorrelations.py
sparkx/Oscar.py
sparkx/Particle.py
sparkx/ParticleObjectStorer.py
sparkx/Utilities.py
sparkx/__init__.py
sparkx/flow/EventPlaneFlow.py
sparkx/flow/FlowInterface.py
sparkx/flow/GenerateFlow.py
sparkx/flow/LeeYangZeroFlow.py
sparkx/flow/PCAFlow.py
sparkx/flow/QCumulantFlow.py
sparkx/flow/ReactionPlaneFlow.py
sparkx/flow/ScalarProductFlow.py
sparkx/flow/__init__.py
sparkx/loader/BaseLoader.py
sparkx/loader/JetscapeLoader.py
sparkx/loader/OscarLoader.py
sparkx/loader/ParticleObjectLoader.py
sparkx/loader/__init__.py
sparkx-2.1.1.dist-info/licenses/LICENSE
sparkx-2.1.1.dist-info/METADATA
sparkx-2.1.1.dist-info/WHEEL
sparkx-2.1.1.dist-info/top_level.txt
sparkx-2.1.1.dist-info/RECORD
