Metadata-Version: 2.4
Name: sparkx
Version: 2.1.1
Summary: Software Package for Analyzing Relativistic Kinematics in Collision eXperiments
Home-page: https://smash-transport.github.io/sparkx/
Download-URL: https://github.com/smash-transport/sparkx
Author: Nils Sass, Hendrik Roch, Niklas Götz, Renata Krupczak, Lucas Constantin
Author-email: Nils Sass <nsass@itp.uni-frankfurt.de>, Hendrik Roch <hroch@wayne.edu>, Niklas Götz <goetz@itp.uni-frankfurt.de>, Renata Krupczak <rkrupczak@physik.uni-bielefeld.de>, Lucas Constantin <constantin@itp.uni-frankfurt.de>
License:                     GNU GENERAL PUBLIC LICENSE
Project-URL: Repository, https://github.com/smash-transport/sparkx
Project-URL: Bug Tracker, https://github.com/smash-transport/sparkx/issues
Project-URL: Documentation, https://smash-transport.github.io/sparkx/
Classifier: Programming Language :: Python :: 3
Classifier: Intended Audience :: Developers
Classifier: Intended Audience :: Science/Research
Classifier: Operating System :: OS Independent
Classifier: Topic :: Scientific/Engineering
Classifier: Natural Language :: English
Requires-Python: >=3.9
License-File: LICENSE
Requires-Dist: particle>=0.25.4
Requires-Dist: numpy>=1.23.5
Requires-Dist: scipy>=1.10.1
Requires-Dist: fastjet>=3.4.2.1
Requires-Dist: matplotlib>=3.7.1
Dynamic: author
Dynamic: download-url
Dynamic: home-page
Dynamic: license-file
